pytest_amaranth_sim-0.1.0.dist-info/METADATA
pytest_amaranth_sim-0.1.0.dist-info/WHEEL
pytest_amaranth_sim-0.1.0.dist-info/entry_points.txt
pytest_amaranth_sim-0.1.0.dist-info/licenses/LICENSE.md
pytest_amaranth_sim/__init__.py
pytest_amaranth_sim/plugin.py
pytest_amaranth_sim/version.txt
pytest_amaranth_sim-0.1.0.dist-info/RECORD
