Metadata-Version: 2.1
Name: pytest-amaranth-sim
Version: 0.1.0
Summary: Fixture to automate running Amaranth simulations
Author-Email: "William D. Jones" <thor0505@comcast.net>
Maintainer-Email: "William D. Jones" <thor0505@comcast.net>
License: BSD 2-Clause License
Classifier: Framework :: Pytest
Classifier: Development Status :: 4 - Beta
Classifier: Intended Audience :: Developers
Classifier: Topic :: Software Development :: Testing
Classifier: Operating System :: OS Independent
Classifier: Programming Language :: Python
Classifier: Programming Language :: Python :: 3.8
Classifier: Programming Language :: Python :: 3.9
Classifier: Programming Language :: Python :: 3.10
Classifier: Programming Language :: Python :: 3.11
Classifier: Programming Language :: Python :: 3.12
Classifier: Programming Language :: Python :: 3 :: Only
Classifier: License :: OSI Approved :: BSD License
Project-URL: Repository, https://github.com/cr1901/pytest-amaranth-sim
Requires-Python: >=3.8
Requires-Dist: pytest>=6.2.0
Requires-Dist: amaranth>=0.5.0
Requires-Dist: in-place>=1.0.0
